{
  "$schema": "http://json-schema.org/draft-06/schema#",
  "type": "array",
  "items": {
    "type": "object",
    "properties": {
      "Full_Name": {
        "description": "Worker's full name.",
        "example": "Alicia Gómez",
        "type": "string"
      },
      "Management_Level": {
        "description": "Management level per Workday.",
        "example": "Manager",
        "type": "string"
      },
      "Effect_Date_for_Current_Pos": {
        "description": "Position effective date (YYYY-MM-DD).",
        "example": "2025-07-01",
        "type": "string",
        "format": "date"
      },
      "Position_ID": {
        "description": "Unique identifier of the position.",
        "example": "POS-00012345",
        "type": "string"
      },
      "Most_Rec_Pos_Change": {
        "description": "Most recent position change date (YYYY-MM-DD).",
        "example": "2025-08-15",
        "type": "string",
        "format": "date"
      },
      "Business_Title": {
        "description": "Worker's business title.",
        "example": "Senior Project Manager",
        "type": "string"
      }
    }
  }
}
